pubkeeper/communication/__init__.py
pubkeeper/communication/client.py
pubkeeper/communication/communication.py
pubkeeper/communication/handler.py
pubkeeper/communication/server.py
pubkeeper/communication/state.py
pubkeeper.communication-0.2.4.dist-info/DESCRIPTION.rst
pubkeeper.communication-0.2.4.dist-info/METADATA
pubkeeper.communication-0.2.4.dist-info/RECORD
pubkeeper.communication-0.2.4.dist-info/WHEEL
pubkeeper.communication-0.2.4.dist-info/metadata.json
pubkeeper.communication-0.2.4.dist-info/top_level.txt
